space_cli/__init__.py
space_cli/main.py
space_cli-0.0.0.dist-info/WHEEL
space_cli-0.0.0.dist-info/METADATA
space_cli-0.0.0.dist-info/RECORD
