Metadata-Version: 2.1
Name: space-cli
Version: 0.0.0
Summary: XYZ
License: Proprietary
Author: Abbas Jafari
Author-email: abbas.jafari@powercoders.org
Requires-Python: >=3.8,<4.0
Classifier: License :: Other/Proprietary License
Classifier: Programming Language :: Python :: 3
Classifier: Programming Language :: Python :: 3.8
Classifier: Programming Language :: Python :: 3.9
